tdrconvert/__init__.py
tdrconvert/all_info.py
tdrconvert/load_devsim.py
tdrconvert/read_tdr.py
tdrconvert/tdr_convert.py
tdrconvert/write_exodus.py
tdrconvert/write_gmsh.py
tdrconvert/write_tetgen.py
tdr_convert-0.1.7.dist-info/LICENSE
tdr_convert-0.1.7.dist-info/METADATA
tdr_convert-0.1.7.dist-info/NOTICE
tdr_convert-0.1.7.dist-info/WHEEL
tdr_convert-0.1.7.dist-info/entry_points.txt
tdr_convert-0.1.7.dist-info/top_level.txt
tdr_convert-0.1.7.dist-info/RECORD
