Metadata-Version: 2.1
Name: tdr-convert
Version: 0.1.7
Summary: tdr-convert: tdr file converter
Home-page: https://github.com/devsim/tdr-convert
Author: Juan Sanchez
Author-email: info@devsim.com
License: Apache License
Project-URL: Bug Tracker, https://github.com/devsim/tdr-convert/issues
Project-URL: Source Code, https://github.com/devsim/tdr-convert
Platform: UNKNOWN
Classifier: Development Status :: 4 - Beta
Classifier: Intended Audience :: Science/Research
Classifier: License :: OSI Approved :: Apache Software License
Classifier: Programming Language :: Python :: 3
Classifier: Topic :: Scientific/Engineering :: Electronic Design Automation (EDA)
License-File: LICENSE
License-File: NOTICE
Requires-Dist: devsim
Requires-Dist: h5py
Requires-Dist: netCDF4
Requires-Dist: numpy
